<?xml version="1.0" encoding="UTF-8"?>
<objects serializationModel="Studio.02.01.00">
	<object class="AudioFile" id="{f84cea5c-3484-4ee7-91de-4870e6fadce0}">
		<property name="assetPath">
			<value>WHOOSH_Short_01_Whistle_mono.wav</value>
		</property>
		<property name="frequencyInKHz">
			<value>44.0999985</value>
		</property>
		<property name="channelCount">
			<value>1</value>
		</property>
		<property name="length">
			<value>0.12272108843537415</value>
		</property>
		<relationship name="masterAssetFolder">
			<destination>{cf03ee0c-d1d3-4704-849a-9a00aa1b5642}</destination>
		</relationship>
	</object>
</objects>
